pygradations/__init__.py
pygradations/core.py
pygradations/interpolation.py
pygradations/utils.py
pygradations-0.1.1.dist-info/METADATA
pygradations-0.1.1.dist-info/WHEEL
pygradations-0.1.1.dist-info/top_level.txt
pygradations-0.1.1.dist-info/RECORD
