Metadata-Version: 2.4
Name: pygradations
Version: 0.1.1
Summary: A Python package for analyzing and manipulating size distributions (gradations) from mineral processing streams
Author-email: Octavio Deliberato Neto <octavio.deliberato@aggxtream.com>
License: MIT
Keywords: mineral processing,size distribution,gradation,sieve analysis
Classifier: Programming Language :: Python :: 3
Requires-Python: >=3.7
Requires-Dist: numpy
Requires-Dist: pandas
Requires-Dist: matplotlib
Requires-Dist: scipy
Requires-Dist: openpyxl
Requires-Dist: importlib-metadata; python_version < "3.12"
Provides-Extra: interactive
Requires-Dist: jupyterlab; extra == "interactive"
Requires-Dist: ipykernel; extra == "interactive"
Requires-Dist: ipywidgets; extra == "interactive"
Provides-Extra: test
Requires-Dist: pytest; extra == "test"
Requires-Dist: pytest-cov; extra == "test"
Provides-Extra: release
Requires-Dist: build; extra == "release"
Requires-Dist: twine; extra == "release"
Provides-Extra: static-code-qa
Requires-Dist: pre-commit; extra == "static-code-qa"
Provides-Extra: dev
Requires-Dist: pygradations[interactive,release,static-code-qa,test]; extra == "dev"
